MANIFEST.in
README.txt
setup.py
docs/HISTORY.txt
docs/LICENSE.txt
src/zeam/__init__.py
src/zeam.form.silva.egg-info/PKG-INFO
src/zeam.form.silva.egg-info/SOURCES.txt
src/zeam.form.silva.egg-info/dependency_links.txt
src/zeam.form.silva.egg-info/entry_points.txt
src/zeam.form.silva.egg-info/namespace_packages.txt
src/zeam.form.silva.egg-info/not-zip-safe
src/zeam.form.silva.egg-info/requires.txt
src/zeam.form.silva.egg-info/top_level.txt
src/zeam/form/__init__.py
src/zeam/form/silva/__init__.py
src/zeam/form/silva/actions.py
src/zeam/form/silva/configure.zcml
src/zeam/form/silva/datamanager.py
src/zeam/form/silva/ftesting.zcml
src/zeam/form/silva/interfaces.py
src/zeam/form/silva/utils.py
src/zeam/form/silva/validation.py
src/zeam/form/silva/xml.py
src/zeam/form/silva/actions_templates/popupwidget.cpt
src/zeam/form/silva/actions_templates/smiactionwidget.cpt
src/zeam/form/silva/actions_templates/smicancelwidget.cpt
src/zeam/form/silva/actions_templates/smilinkactionwidget.cpt
src/zeam/form/silva/actions_templates/smiremoverwidget.cpt
src/zeam/form/silva/form/__init__.py
src/zeam/form/silva/form/popup.py
src/zeam/form/silva/form/public.py
src/zeam/form/silva/form/smi.py
src/zeam/form/silva/form/zmi.py
src/zeam/form/silva/form/popup_templates/restformtemplate.cpt
src/zeam/form/silva/form/public_templates/publicformtemplate.cpt
src/zeam/form/silva/form/smi_templates/smicomposedformtemplate.cpt
src/zeam/form/silva/form/smi_templates/smiformportlets.cpt
src/zeam/form/silva/form/smi_templates/smiformtemplate.cpt
src/zeam/form/silva/form/smi_templates/smisubformgrouptemplate.cpt
src/zeam/form/silva/form/smi_templates/smisubformtemplate.cpt
src/zeam/form/silva/form/smi_templates/smisubtableformtemplate.cpt
src/zeam/form/silva/form/smi_templates/smitableformtemplate.cpt
src/zeam/form/silva/form/static/arrows.png
src/zeam/form/silva/form/static/public.css
src/zeam/form/silva/form/static/public.min.css
src/zeam/form/silva/form/static/smi.js
src/zeam/form/silva/form/static/smi.min.js
src/zeam/form/silva/form/static/zmi.css
src/zeam/form/silva/form/static/zmi.js
src/zeam/form/silva/form/static/zmi.min.css
src/zeam/form/silva/form/static/zmi.min.js
src/zeam/form/silva/form/zmi_templates/zmicomposedformtemplate.pt
src/zeam/form/silva/form/zmi_templates/zmiformtemplate.pt
