Metadata-Version: 1.1
Name: zeam.form.silva
Version: 2.0.5
Summary: Integration of the Grok-based Zeam Form system into Silva
Home-page: https://github.com/silvacms/zeam.form.silva
Author: Sylvain Viollon
Author-email: thefunny@gmail.com
License: BSD
Keywords: grok form framework silva
Platform: UNKNOWN
Classifier: Programming Language :: Python
Classifier: Topic :: Software Development :: Libraries :: Python Modules
